crane/__init__.py
crane/app.py
crane/app_util.py
crane/config.py
crane/data.py
crane/exceptions.py
crane/wsgi.py
crane/api/__init__.py
crane/api/images.py
crane/api/repository.py
crane/data/default_config.conf
crane/search/__init__.py
crane/search/base.py
crane/search/gsa.py
crane/search/solr.py
crane/static/css/bootstrap-treeview.min.css
crane/static/css/bootstrap.css
crane/static/css/bootstrap.css.map
crane/static/css/jquery.min.map
crane/static/css/patternfly.min.css
crane/static/fonts/FontAwesome.otf
crane/static/fonts/OpenSans-Bold-webfont.eot
crane/static/fonts/OpenSans-Bold-webfont.svg
crane/static/fonts/OpenSans-Bold-webfont.ttf
crane/static/fonts/OpenSans-Bold-webfont.woff
crane/static/fonts/OpenSans-BoldItalic-webfont.eot
crane/static/fonts/OpenSans-BoldItalic-webfont.svg
crane/static/fonts/OpenSans-BoldItalic-webfont.ttf
crane/static/fonts/OpenSans-BoldItalic-webfont.woff
crane/static/fonts/OpenSans-ExtraBold-webfont.eot
crane/static/fonts/OpenSans-ExtraBold-webfont.svg
crane/static/fonts/OpenSans-ExtraBold-webfont.ttf
crane/static/fonts/OpenSans-ExtraBold-webfont.woff
crane/static/fonts/OpenSans-ExtraBoldItalic-webfont.eot
crane/static/fonts/OpenSans-ExtraBoldItalic-webfont.svg
crane/static/fonts/OpenSans-ExtraBoldItalic-webfont.ttf
crane/static/fonts/OpenSans-ExtraBoldItalic-webfont.woff
crane/static/fonts/OpenSans-Italic-webfont.eot
crane/static/fonts/OpenSans-Italic-webfont.svg
crane/static/fonts/OpenSans-Italic-webfont.ttf
crane/static/fonts/OpenSans-Italic-webfont.woff
crane/static/fonts/OpenSans-Light-webfont.eot
crane/static/fonts/OpenSans-Light-webfont.svg
crane/static/fonts/OpenSans-Light-webfont.ttf
crane/static/fonts/OpenSans-Light-webfont.woff
crane/static/fonts/OpenSans-LightItalic-webfont.eot
crane/static/fonts/OpenSans-LightItalic-webfont.svg
crane/static/fonts/OpenSans-LightItalic-webfont.ttf
crane/static/fonts/OpenSans-LightItalic-webfont.woff
crane-2.1.dist-info/DESCRIPTION.rst
crane-2.1.dist-info/METADATA
crane-2.1.dist-info/RECORD
crane-2.1.dist-info/WHEEL
crane-2.1.dist-info/metadata.json
crane-2.1.dist-info/top_level.txt
