Metadata-Version: 2.0
Name: crane
Version: 2.1
Summary: docker-registry-like API with redirection, as a wsgi app
Home-page: http://www.pulpproject.org
Author: Pulp Team
Author-email: pulp-list@redhat.com
License: GPLv2+
Platform: UNKNOWN
Requires-Dist: Flask (>=0.9)
Requires-Dist: setuptools
